{
  "slug": "yubikey-setup-guide",
  "title": "YubiKey Setup Guide: How to Use a Hardware Security Key for Maximum Protection",
  "date": "2026-05-08",
  "category": "2FA",
  "readingTime": "12 min",
  "tags": [
    "yubikey",
    "hardware security key",
    "2FA",
    "FIDO2",
    "account security"
  ],
  "excerpt": "A YubiKey is the strongest form of two-factor authentication available to consumers -- it physically blocks phishing attacks that defeat app-based 2FA. This guide walks you through choosing the right YubiKey, setting it up on your most important accounts, and building a backup plan so you never get locked out.",
  "content": "<h2>Why a Hardware Key Beats Every Other Form of 2FA</h2>\n<p>Most people protect their accounts with an authenticator app or SMS codes. Both are better than nothing, but both can be defeated by a determined attacker. SMS codes can be intercepted via SIM-swapping — a method where an attacker convinces your mobile carrier to transfer your phone number to a SIM card they control. Once they have your number, every SMS authentication code goes straight to them. Authenticator app codes have a different vulnerability: if you enter a valid code on a convincing phishing site, the attacker can replay it in real time to access your real account before the 30-second window expires.</p>\n<p>A hardware security key like a YubiKey operates on an entirely different principle. It uses a cryptographic challenge-response protocol — specifically FIDO2/WebAuthn — tied to the exact domain you are logging into. Your browser sends the site's origin to the key, the key signs a challenge that proves physical possession, and the signed response is verified server-side. Even if an attacker tricks you onto a fake Google login page at g00gle.com, your YubiKey will refuse to authenticate because the domain does not match what was registered. Phishing attacks are mathematically impossible, not just unlikely.</p>\n<p>This is why security teams at companies like Google, Facebook, and Cloudflare require hardware keys for all employees. After Google deployed hardware keys company-wide in 2017, they reported zero successful phishing attacks on employee accounts. You can have the same level of protection on your personal accounts today.</p>\n\n<h2>How a YubiKey Actually Works</h2>\n<p>Inside a YubiKey is a secure element — a tamper-resistant chip — that stores cryptographic private keys. When you register a YubiKey with a website, the key generates a unique public-private key pair for that site. The private key never leaves the device. When you log in, the site sends a random challenge; your YubiKey signs it with the private key and returns the signature. The site verifies the signature using the stored public key. Without physical possession of the YubiKey, the signature cannot be produced.</p>\n<p>YubiKeys support several protocols. FIDO2/WebAuthn is the modern standard used by Google, GitHub, Microsoft, and hundreds of other services — this is what you should use wherever possible. FIDO U2F is the older version, still widely supported. TOTP (time-based one-time passwords) is also supported by YubiKey 5 series models, which means you can store your authenticator app codes on the key itself for an extra layer of protection. PIV (smart card) support enables certificate-based authentication on corporate networks and macOS/Windows login. OTP (one-time password) is a legacy mode that generates Yubico-format codes — useful for some older systems.</p>\n<p>For most people, FIDO2 is all you need to know. Register your key with your accounts using the security key option, and the browser handles the rest automatically.</p>\n\n<h2>Choosing the Right YubiKey Model</h2>\n<p>Yubico makes several models designed for different use cases. The <strong>YubiKey 5 NFC</strong> is the best all-around choice for most people at around $55. It connects via USB-A and also supports NFC, so you can tap it against your phone to authenticate on mobile. It supports FIDO2/WebAuthn, TOTP, PIV, and OTP — essentially every protocol you might need.</p>\n<p>The <strong>YubiKey 5C NFC</strong> is identical but uses USB-C instead of USB-A, making it a better fit for modern MacBooks, Chromebooks, and USB-C Android phones. If your primary computer has only USB-C ports, this is the model to get. The <strong>YubiKey 5Ci</strong> has both USB-C and a Lightning connector, specifically designed for iPhone users who want wired authentication without NFC. The <strong>Security Key NFC</strong> is Yubico's budget option at around $29 — it handles FIDO2 and WebAuthn only, which is enough for Gmail, GitHub, and Dropbox, but it won't work for TOTP or legacy enterprise applications.</p>\n<p><strong>Always buy two keys.</strong> This is non-negotiable. If you register a single key and lose it, you risk being locked out of every account where it's your only 2FA method. Register a second key on every important account and store it somewhere secure and separate from your primary key — a fireproof safe, a bank safe deposit box, or a trusted family member's home are all solid options.</p>\n\n<h2>Setting Up Your YubiKey on Key Accounts</h2>\n<p>The registration process follows the same general pattern across services: navigate to account security settings, find the 2FA or security key option, click register, insert your YubiKey when prompted, and touch the gold disc to confirm. Here are step-by-step instructions for the accounts that matter most.</p>\n<p><strong>Google Account:</strong> Go to myaccount.google.com → Security → 2-Step Verification → Add security key. Insert your YubiKey and touch the button. Name the key something memorable like \"YubiKey Primary.\" Repeat the process to register your backup key. After setup, consider removing your phone number from your Google account — SMS is the weakest link, and if it's still there, an attacker can use SIM-swapping to bypass your hardware key.</p>\n<p><strong>GitHub:</strong> Go to Settings → Password and authentication → Two-factor authentication → Add security key. GitHub fully supports FIDO2 so any modern YubiKey works. Before finishing setup, generate and print your recovery codes — store them offline in a secure location. Losing access to your GitHub account without recovery codes can mean losing years of work and contributions.</p>\n<p><strong>Microsoft Account:</strong> Go to account.microsoft.com → Security → Advanced security options → Add a new way to sign in → Use a security key. Touch your key when Windows Hello prompts you. You can also configure Windows Hello to require the key for computer login, which we'll cover below.</p>\n<p><strong>Dropbox, Facebook, Twitter/X, LinkedIn:</strong> All support security keys under their security or privacy settings. Look for the Two-Factor Authentication section, then select Security Key or Hardware Key. If you use <a href=\"https://1password.com\" rel=\"noopener sponsored\">1Password</a> as your password manager, you can configure it to require a YubiKey touch when unlocking your vault — adding a physical layer on top of your master password.</p>\n\n<h2>Using YubiKey for Computer Login on macOS and Windows</h2>\n<p>One of the most overlooked use cases for a YubiKey is securing your computer login itself. Even a strong password can be shoulder-surfed or captured by malware. Requiring a physical key touch to unlock your machine closes that gap.</p>\n<p><strong>On macOS:</strong> YubiKey supports macOS login via the Yubico Login for macOS application (available free at yubico.com). After installation and configuration, your Mac will prompt for both your password and a YubiKey touch at login. This works for local accounts; FileVault pre-boot is a separate layer that requires additional configuration described in Yubico's documentation.</p>\n<p><strong>On Windows:</strong> Windows Hello for Business supports FIDO2 security keys natively on Windows 10 and 11. In Settings → Accounts → Sign-in options, you can add a Security Key and configure it as a login method. For enterprise users, Microsoft Entra ID (formerly Azure AD) supports hardware key sign-in to web applications and Windows login across managed devices.</p>\n\n<h2>Using Your YubiKey on Mobile Devices</h2>\n<p>NFC-equipped YubiKeys — the 5 NFC, 5C NFC, and Security Key NFC — work seamlessly with smartphones. On Android, NFC authentication is supported natively in Chrome and most major apps. To use it, hold the key against the back of your phone near the camera module; the phone will detect it via NFC and complete authentication. On iPhone, NFC support for security keys arrived with iOS 13.3 and works in Safari and Chrome for FIDO2-compatible sites.</p>\n<p>For iPhone users who prefer a wired connection, the YubiKey 5Ci plugs directly into the Lightning port and is supported by the Yubico Authenticator app on iOS. This app also lets you store TOTP codes on the key — rather than storing seeds on your phone where they could be extracted by malware, the codes are generated by the key itself and displayed only when it's physically connected or tapped.</p>\n<p>Use our <a href=\"/\">free password generator</a> to create strong unique passwords for the email addresses and recovery accounts linked to your mobile authentication setup. Those accounts become the backup entry point to everything else, so they deserve the same level of protection.</p>\n\n<h2>Building a Backup Plan and Recovery Strategy</h2>\n<p>The biggest risk with hardware key authentication is accidental lockout. Handle this before it happens, not after. The following checklist covers the key steps:</p>\n<ul>\n<li>Register at least two physical YubiKeys on every important account</li>\n<li>Download and securely store recovery codes for services that provide them (GitHub, Google, etc.)</li>\n<li>Store recovery codes in an encrypted note inside your password manager AND as a printed copy in a fireproof safe</li>\n<li>Verify that at least one backup authentication method exists for every account — not SMS if possible</li>\n<li>Test your backup key before an emergency — log out and log back in using only the backup key to confirm it works</li>\n<li>Check 2fa.directory annually to see if new accounts you're using have added hardware key support</li>\n</ul>\n<p>For accounts that don't yet support hardware keys, use a TOTP authenticator app (Google Authenticator, Aegis on Android, or Yubico Authenticator). It is meaningfully stronger than SMS, even if not as secure as a hardware key. Never use SMS as your only 2FA method on accounts that hold financial or personally identifiable information.</p>\n<p>Consider a <a href=\"https://www.kqzyfj.com/click-101754888-17262576\" rel=\"noopener sponsored\">NordPass</a> subscription to keep your recovery codes, backup keys, and account security notes in an encrypted vault that's accessible from any device. Combining a high-quality password manager with a hardware security key covers the two most common attack vectors — stolen passwords and phishing — in a practical everyday workflow.</p>\n\n<h2>YubiKey Quick-Setup Checklist</h2>\n<p>Use this checklist when setting up a new YubiKey or auditing your existing hardware key security:</p>\n<ul>\n<li>☐ Purchased two YubiKey 5 NFC (or 5C NFC) devices</li>\n<li>☐ Registered both keys on Google account — phone number removed from recovery</li>\n<li>☐ Registered both keys on GitHub — offline recovery codes printed and stored</li>\n<li>☐ Registered both keys on Microsoft account</li>\n<li>☐ Registered both keys on password manager (1Password or NordPass)</li>\n<li>☐ Registered both keys on any financial accounts that support hardware keys</li>\n<li>☐ Backup key stored in a separate physical location</li>\n<li>☐ Tested backup key by completing a full login flow</li>\n<li>☐ Recovery codes stored in password manager AND offline</li>\n<li>☐ All SMS 2FA replaced with hardware key or TOTP where possible</li>\n</ul>\n\n<h2>Recommended Tools</h2>\n<p>For storing the passwords and recovery codes that complement your YubiKey setup, we recommend <a href=\"https://www.kqzyfj.com/click-101754888-17262576\" rel=\"noopener sponsored\">NordPass</a> (zero-knowledge encryption, free tier available) or <a href=\"https://1password.com\" rel=\"noopener sponsored\">1Password</a> for families or teams who want shared vault features alongside hardware key enforcement.</p>\n<p>See our full <a href=\"/recommended-tools\">security tools guide</a> for more recommendations on building a complete personal security stack.</p>"
}